{
  "proses": [
    {
      "invoice": "SPY1774670566TBUB",
      "ref_id": "GM-XQI0M7PE",
      "contact": "teamclugo@gmail.com",
      "order_id": "QR1774669810204",
      "product_name": "Viu",
      "variant_name": "3 Bulan",
      "variant_id": 786,
      "amount": 3,
      "seller_note": "LOGIN MENGGUNAKAN EMAIL DI VIU\n\nDILARANG OTAK ATIK PEMBAYARAN DAN GANTI AKUN\nPAKAI 1 PERANGKAT AJA!\n\n---\nCatatan Admin:\nLOGIN MENGGUNAKAN EMAIL DI VIU\n\nDILARANG OTAK ATIK PEMBAYARAN DAN GANTI AKUN\nPAKAI 1 PERANGKAT AJA!",
      "created_at": "2026-03-28T04:02:47.929Z",
      "email_notification_sent": true,
      "api_response": {
        "message": "OK",
        "data": {
          "invoice": "SPY1774670566TBUB",
          "ref_id": "GM-XQI0M7PE",
          "status": "paid",
          "price": 950,
          "fees": null,
          "amount": 950,
          "contact": "bagusbahril30@gmail.com",
          "created_at": "2026-03-28T11:02:46+07:00"
        }
      }
    }
  ]
}