{
  "proses": [
    {
      "invoice": "SPY1775182460OOVX",
      "ref_id": "GM-FIM2JUTR",
      "contact": "repaalinaa613@gmail.com",
      "order_id": "QR1775182419453",
      "product_name": "Alight Motion",
      "variant_name": "1 Tahun [ Android ]",
      "variant_id": 8,
      "amount": 4313,
      "seller_note": "SILAHKAN IKUTI TUTORIAL LOGIN DIBAWAH INI :\n\nhttps://youtu.be/YfT2dggAGqM?si=L6XzymPsv5D5PLMf\n\n---\nCatatan Admin:\nSILAHKAN IKUTI TUTORIAL LOGIN DIBAWAH INI :\n\nhttps://youtu.be/YfT2dggAGqM?si=L6XzymPsv5D5PLMf",
      "created_at": "2026-04-03T02:14:24.034Z",
      "email_notification_sent": true,
      "api_response": {
        "message": "OK",
        "data": {
          "invoice": "SPY1775182460OOVX",
          "ref_id": "GM-FIM2JUTR",
          "status": "paid",
          "price": 960,
          "fees": null,
          "amount": 960,
          "contact": "bagusbahril30@gmail.com",
          "created_at": "2026-04-03T09:14:20+07:00"
        }
      }
    }
  ]
}