[
  {
    "email": "zikribara623@gmail.com",
    "order_created": "2026-07-06T05:21:55.408Z"
  },
  {
    "email": "deaandanita7@gmail.com",
    "order_created": "2026-07-06T05:16:56.795Z"
  },
  {
    "email": "adisuardiadisuardi2@gmail.com",
    "order_created": "2026-07-06T04:54:59.217Z"
  },
  {
    "email": "sandii4sanddi@gmail.com",
    "order_created": "2026-07-06T04:13:37.068Z"
  },
  {
    "email": "akbarrizkifahreza92@gmail.com",
    "order_created": "2026-07-06T03:59:54.975Z"
  },
  {
    "email": "amgacor238@gmail.com",
    "order_created": "2026-07-06T02:49:21.248Z"
  },
  {
    "email": "kmoretti161@gmail.com",
    "order_created": "2026-07-06T02:47:13.708Z"
  },
  {
    "email": "salusamisanju@gmail.com",
    "order_created": "2026-07-06T02:24:52.961Z"
  },
  {
    "email": "sumsitaita@gmail.com",
    "order_created": "2026-07-06T00:45:39.167Z"
  },
  {
    "email": "adeliaaaputrii751@gmail.com",
    "order_created": "2026-07-06T00:04:07.969Z"
  },
  {
    "email": "rahimhabiburrahim@gmail.com",
    "order_created": "2026-07-05T23:14:16.944Z"
  },
  {
    "email": "udembele024@gmail.com",
    "order_created": "2026-07-05T22:38:35.544Z"
  },
  {
    "email": "luzivertkall@gmail.com",
    "order_created": "2026-07-05T22:11:43.901Z"
  },
  {
    "email": "hengki200311@gmail.com",
    "order_created": "2026-07-05T19:44:58.348Z"
  },
  {
    "email": "aldestzyy@gmail.com",
    "order_created": "2026-07-05T19:14:04.330Z"
  },
  {
    "email": "abdulhaqmauladappa@gmail.com",
    "order_created": "2026-07-05T18:04:05.020Z"
  },
  {
    "email": "ndraa969@gmail.com",
    "order_created": "2026-07-05T16:22:11.867Z"
  },
  {
    "email": "fathurfirmansyahsah@gmail.com",
    "order_created": "2026-07-05T14:25:54.732Z"
  },
  {
    "email": "alvinefendi566@gmail.com",
    "order_created": "2026-07-05T14:08:31.571Z"
  },
  {
    "email": "Farezailham7@gmail.com",
    "order_created": "2026-07-05T12:47:24.905Z"
  }
]