{
  "pending_orders": [
    {
      "order_id": "QR1778986970562",
      "email": "newjimelyeuh@gmail.com",
      "product_name": "Alight Motion [1 Tahun]",
      "total": 4297,
      "created_at": "2026-05-17T03:02:52.149Z",
      "expired_at": "2026-05-17T04:02:48.825Z",
      "payment_ref_no": "QR1778986970562"
    },
    {
      "order_id": "QR1778989694897",
      "email": "vywyh50@gmail.com",
      "product_name": "Alight Motion [1 Tahun]",
      "total": 3779,
      "created_at": "2026-05-17T03:48:16.518Z",
      "expired_at": "2026-05-17T04:48:13.066Z",
      "payment_ref_no": "QR1778989694897"
    }
  ]
}