{
  "pending_orders": [
    {
      "order_id": "QR1779290752622",
      "email": "sairulilham440@gmail.com",
      "product_name": "Alight Motion [1 Tahun]",
      "total": 4207,
      "created_at": "2026-05-20T15:25:54.446Z",
      "expired_at": "2026-05-20T16:25:49.679Z",
      "payment_ref_no": "QR1779290752622"
    },
    {
      "order_id": "QR1779291864837",
      "email": "galangbuluex@gmail.com",
      "product_name": "Alight Motion [1 Tahun]",
      "total": 3989,
      "created_at": "2026-05-20T15:44:27.081Z",
      "expired_at": "2026-05-20T16:44:23.169Z",
      "payment_ref_no": "QR1779291864837"
    }
  ]
}