{
  "pending_orders": [
    {
      "order_id": "1090983",
      "email": "muhammadfauzy787@gmail.com",
      "product_name": "Alight Motion [1 Tahun]",
      "total": 4057,
      "created_at": "2026-07-20T20:46:33.724Z",
      "expired_at": "2026-07-20T20:51:17.229Z",
      "payment_ref_no": "1090983",
      "qr_url": "https://sp39586.serpul.co.id/storage/image/qris/qris_17845803901090983.png"
    },
    {
      "order_id": "1090992",
      "email": "tans314242@gmail.com",
      "product_name": "Alight Motion [1 Tahun]",
      "total": 4445,
      "created_at": "2026-07-20T22:41:24.598Z",
      "expired_at": "2026-07-20T22:46:17.505Z",
      "payment_ref_no": "1090992",
      "qr_url": "https://sp39586.serpul.co.id/storage/image/qris/qris_17845872811090992.png"
    },
    {
      "order_id": "1090998",
      "email": "fiannn312@gmail.com",
      "product_name": "Alight Motion [1 Tahun]",
      "total": 4969,
      "created_at": "2026-07-20T23:01:46.361Z",
      "expired_at": "2026-07-20T23:06:39.370Z",
      "payment_ref_no": "1090998",
      "qr_url": "https://sp39586.serpul.co.id/storage/image/qris/qris_17845885031090998.png"
    },
    {
      "order_id": "1090999",
      "email": "rereiqila12@gmail.com",
      "product_name": "Alight Motion [1 Tahun]",
      "total": 4416,
      "created_at": "2026-07-20T23:02:32.438Z",
      "expired_at": "2026-07-20T23:07:26.912Z",
      "payment_ref_no": "1090999",
      "qr_url": "https://sp39586.serpul.co.id/storage/image/qris/qris_17845885491090999.png"
    },
    {
      "order_id": "1091000",
      "email": "fiannn312@gmail.com",
      "product_name": "Alight Motion [1 Tahun]",
      "total": 4235,
      "created_at": "2026-07-20T23:08:36.007Z",
      "expired_at": "2026-07-20T23:13:29.422Z",
      "payment_ref_no": "1091000",
      "qr_url": "https://sp39586.serpul.co.id/storage/image/qris/qris_17845889131091000.png"
    },
    {
      "order_id": "1091010",
      "email": "paellamprem@gmail.com",
      "product_name": "Alight Motion [1 Tahun]",
      "total": 4183,
      "created_at": "2026-07-21T00:17:14.170Z",
      "expired_at": "2026-07-21T00:22:06.790Z",
      "payment_ref_no": "1091010",
      "qr_url": "https://sp39586.serpul.co.id/storage/image/qris/qris_17845930301091010.png"
    }
  ]
}