{
  "order_id": "1089214",
  "email": "sabilillahazhiimi@gmail.com",
  "product_name": "Alight Motion [1 Tahun]",
  "price": 3500,
  "fee": 1490,
  "total": 4990,
  "ip_address": "202.1.24.35",
  "status": "pending",
  "payment_ref_no": "1089214",
  "payment_url": "https://www.goodmotion.id/invoice/1089214",
  "qr_url": "https://sp39586.serpul.co.id/storage/image/qris/qris_17844259081089214.png",
  "qr_image": "https://sp39586.serpul.co.id/storage/image/qris/qris_17844259081089214.png",
  "created_at": "2026-07-19T01:51:50.084Z",
  "expired_at": "2026-07-19T01:56:44.278Z"
}