{
  "order_id": "1090230",
  "email": "testme12345@gmail.com",
  "product_name": "Alight Motion [1 Tahun]",
  "price": 3500,
  "fee": 814,
  "total": 4314,
  "ip_address": "103.143.106.114",
  "status": "pending",
  "payment_ref_no": "1090230",
  "payment_url": "https://www.goodmotion.id/invoice/1090230",
  "qr_url": "https://sp39586.serpul.co.id/storage/image/qris/qris_17845028341090230.png",
  "qr_image": "https://sp39586.serpul.co.id/storage/image/qris/qris_17845028341090230.png",
  "created_at": "2026-07-19T23:13:56.356Z",
  "expired_at": "2026-07-19T23:18:52.428Z"
}