{
  "order_id": "4035528",
  "email": "syauqiahmadantoni@gmail.com",
  "product_name": "Alight Motion [1 Tahun]",
  "price": 3500,
  "fee": 1488,
  "total": 4988,
  "ip_address": "182.4.69.134",
  "status": "success",
  "payment_ref_no": "4035528",
  "payment_url": "https://www.goodpay.zone.id/invoice/4035528",
  "qr_url": "https://gateway.okeconnect.com/edcqris/20260626/2715307-62661a0dcbd3743c5ac1f3bd8ca8d05b3c952110-4035528-4988.png",
  "qr_image": "https://gateway.okeconnect.com/edcqris/20260626/2715307-62661a0dcbd3743c5ac1f3bd8ca8d05b3c952110-4035528-4988.png",
  "created_at": "2026-06-26T07:10:48.461Z",
  "expired_at": "2026-06-26T07:15:44.241Z",
  "paid_at": "2026-06-26T07:12:45.323Z",
  "email_sent": true,
  "delivered_account": {
    "email": "gmyeiya8jz8w@goodmail.my.id",
    "link_login": "gmyeiya8jz8w"
  },
  "payment_method": "QRIS",
  "raw_payload": {
    "id": 4035528,
    "amount": 4988,
    "status": "success"
  }
}