{
  "order_id": "4058595",
  "email": "flowieegwey@gmail.com",
  "product_name": "Alight Motion [1 Tahun]",
  "price": 3500,
  "fee": 943,
  "total": 4443,
  "ip_address": "103.157.63.10",
  "status": "pending",
  "payment_ref_no": "4058595",
  "payment_url": "https://www.goodpay.zone.id/invoice/4058595",
  "qr_url": "https://gateway.okeconnect.com/edcqris/20260704/2715307-62661a0dcbd3743c5ac1f3bd8ca8d05b3c952110-4058595-4443.png",
  "qr_image": "https://gateway.okeconnect.com/edcqris/20260704/2715307-62661a0dcbd3743c5ac1f3bd8ca8d05b3c952110-4058595-4443.png",
  "created_at": "2026-07-04T02:25:19.533Z",
  "expired_at": "2026-07-04T02:30:15.536Z"
}