{
  "order_id": "4061723",
  "email": "sayanyobadulu19@gmail.com",
  "product_name": "Alight Motion [1 Tahun]",
  "price": 3500,
  "fee": 808,
  "total": 4308,
  "ip_address": "202.58.72.134",
  "status": "pending",
  "payment_ref_no": "4061723",
  "payment_url": "https://www.goodpay.zone.id/invoice/4061723",
  "qr_url": "https://gateway.okeconnect.com/edcqris/20260705/2715307-62661a0dcbd3743c5ac1f3bd8ca8d05b3c952110-4061723-4308.png",
  "qr_image": "https://gateway.okeconnect.com/edcqris/20260705/2715307-62661a0dcbd3743c5ac1f3bd8ca8d05b3c952110-4061723-4308.png",
  "created_at": "2026-07-05T09:02:55.732Z",
  "expired_at": "2026-07-05T09:07:51.681Z"
}