{
  "order_id": "4066612",
  "email": "shohwahfassah3@gmail.com",
  "product_name": "Alight Motion [1 Tahun]",
  "price": 3500,
  "fee": 1482,
  "total": 4982,
  "ip_address": "182.2.179.249",
  "status": "pending",
  "payment_ref_no": "4066612",
  "payment_url": "https://www.goodpay.zone.id/invoice/4066612",
  "qr_url": "https://gateway.okeconnect.com/edcqris/20260707/2715307-62661a0dcbd3743c5ac1f3bd8ca8d05b3c952110-4066612-4982.png",
  "qr_image": "https://gateway.okeconnect.com/edcqris/20260707/2715307-62661a0dcbd3743c5ac1f3bd8ca8d05b3c952110-4066612-4982.png",
  "created_at": "2026-07-07T06:26:48.334Z",
  "expired_at": "2026-07-07T06:31:44.070Z"
}