{
  "order_id": "4078938",
  "email": "test@gmail.com",
  "product_name": "Alight Motion [1 Tahun]",
  "price": 3500,
  "fee": 1002,
  "total": 4502,
  "ip_address": "208.77.246.41",
  "status": "pending",
  "payment_ref_no": "4078938",
  "payment_url": "https://www.goodmotion.id/invoice/4078938",
  "qr_url": "https://gateway.okeconnect.com/edcqris/20260712/2715307-62661a0dcbd3743c5ac1f3bd8ca8d05b3c952110-4078938-4502.png",
  "qr_image": "https://gateway.okeconnect.com/edcqris/20260712/2715307-62661a0dcbd3743c5ac1f3bd8ca8d05b3c952110-4078938-4502.png",
  "created_at": "2026-07-12T05:04:32.758Z",
  "expired_at": "2026-07-12T05:09:28.534Z"
}