{
  "order_id": "4095407",
  "email": "rapjegurun@gmail.com",
  "product_name": "Alight Motion [1 Tahun]",
  "price": 3500,
  "fee": 1126,
  "total": 4626,
  "ip_address": "110.136.86.151",
  "status": "pending",
  "payment_ref_no": "4095407",
  "payment_url": "https://www.goodmotion.id/invoice/4095407",
  "qr_url": "https://gateway.okeconnect.com/edcqris/20260718/2715307-62661a0dcbd3743c5ac1f3bd8ca8d05b3c952110-4095407-4626.png",
  "qr_image": "https://gateway.okeconnect.com/edcqris/20260718/2715307-62661a0dcbd3743c5ac1f3bd8ca8d05b3c952110-4095407-4626.png",
  "created_at": "2026-07-18T13:18:17.556Z",
  "expired_at": "2026-07-18T13:23:13.561Z"
}