{
  "order_id": "4106687",
  "email": "aliyajelsitia10@gmail.com",
  "product_name": "Alight Motion [1 Tahun]",
  "price": 3500,
  "fee": 1187,
  "total": 4687,
  "ip_address": "180.254.226.173",
  "status": "success",
  "payment_ref_no": "4106687",
  "payment_url": "https://www.goodmotion.id/invoice/4106687",
  "qr_url": "https://gateway.okeconnect.com/edcqris/20260723/2715307-62661a0dcbd3743c5ac1f3bd8ca8d05b3c952110-4106687-4687.png",
  "qr_image": "https://gateway.okeconnect.com/edcqris/20260723/2715307-62661a0dcbd3743c5ac1f3bd8ca8d05b3c952110-4106687-4687.png",
  "created_at": "2026-07-23T06:27:21.533Z",
  "expired_at": "2026-07-23T06:32:17.142Z",
  "paid_at": "2026-07-23T06:29:34.217Z",
  "email_sent": true,
  "delivered_account": {
    "old_stock_email": "gm-p0i5sr8@goodmail.my.id",
    "status": "PREMIUM ACTIVE"
  },
  "payment_method": "QRIS",
  "raw_payload": {
    "id": 4106687,
    "amount": 4687,
    "status": "success"
  }
}